Metadata-Version: 2.4
Name: code-understanding-mcp-server
Version: 0.1.8
Summary: MCP server for code understanding and context generation
Author-email: Tim Kitchens <codingthefuturewithai@gmail.com>
License: MIT
Classifier: Development Status :: 3 - Alpha
Classifier: Intended Audience :: Developers
Classifier: License :: OSI Approved :: MIT License
Classifier: Programming Language :: Python :: 3
Classifier: Programming Language :: Python :: 3.11
Classifier: Programming Language :: Python :: 3.12
Classifier: Topic :: Software Development :: Libraries :: Python Modules
Requires-Python: <3.13,>=3.11
Requires-Dist: mcp==1.6.0
Requires-Dist: mcp[cli]==1.6.0
Requires-Dist: gitpython==3.1.44
Requires-Dist: langchain==0.3.25
Requires-Dist: aiohttp==3.11.18
Requires-Dist: pyyaml==6.0.2
Requires-Dist: typing-extensions==4.13.2
Requires-Dist: pytest==8.4.0
Requires-Dist: pytest-asyncio==1.0.0
Requires-Dist: pytest-cov==6.2.1
Requires-Dist: pathspec==0.12.1
Requires-Dist: aider-chat==0.84.0
Requires-Dist: configargparse==1.7.1
Requires-Dist: identify==2.6.12
Requires-Dist: lizard==1.17.31
Requires-Dist: debugpy==1.8.14
Requires-Dist: platformdirs==4.3.8
Requires-Dist: filelock==3.18.0
Provides-Extra: dev
Requires-Dist: pytest==8.4.0; extra == "dev"
Requires-Dist: pytest-asyncio==1.0.0; extra == "dev"
Requires-Dist: pytest-cov==6.2.1; extra == "dev"
Requires-Dist: black==25.1.0; extra == "dev"
Requires-Dist: isort==6.0.1; extra == "dev"
Requires-Dist: mypy==1.16.1; extra == "dev"
Requires-Dist: pre-commit==4.2.0; extra == "dev"
